{
    "bi": {
        "\"shaking.\"": {
            "to": 1.0
        }, 
        "#obese#": {
            "is": 1.0
        }, 
        "(": {
            "insulin": 1.0
        }, 
        ")": {
            "Glargine": 1.0
        }, 
        ",": {
            "#obese#": 0.015384615384615385, 
            "1.8": 0.015384615384615385, 
            "1064": 0.015384615384615385, 
            "130": 0.015384615384615385, 
            "140/82": 0.015384615384615385, 
            "2002": 0.015384615384615385, 
            "400": 0.015384615384615385, 
            "92": 0.015384615384615385, 
            "BRAYE": 0.015384615384615385, 
            "C": 0.015384615384615385, 
            "Cardiomyopathy": 0.015384615384615385, 
            "E": 0.015384615384615385, 
            "Lantus": 0.015384615384615385, 
            "Mettee": 0.015384615384615385, 
            "SPIESS": 0.015384615384615385, 
            "Soft": 0.015384615384615385, 
            "VIDA": 0.015384615384615385, 
            "a.c.": 0.015384615384615385, 
            "admission": 0.015384615384615385, 
            "b.i.d.": 0.12307692307692308, 
            "block": 0.015384615384615385, 
            "breakfast": 0.015384615384615385, 
            "cramps": 0.015384615384615385, 
            "daily": 0.2153846153846154, 
            "days": 0.015384615384615385, 
            "dinner": 0.015384615384615385, 
            "enlargement": 0.015384615384615385, 
            "insufficiency": 0.015384615384615385, 
            "lunch": 0.015384615384615385, 
            "minute": 0.015384615384615385, 
            "night": 0.015384615384615385, 
            "p.r.n.": 0.015384615384615385, 
            "polydipsia": 0.015384615384615385, 
            "polyuria": 0.015384615384615385, 
            "q.a.m.": 0.03076923076923077, 
            "t.i.d.": 0.03076923076923077, 
            "transplant": 0.015384615384615385, 
            "units": 0.07692307692307693, 
            "vision": 0.015384615384615385
        }, 
        "0.25": {
            "Rocaltrol": 1.0
        }, 
        "0.3": {
            "colchicine": 1.0
        }, 
        "0.6": {
            "colchicine": 1.0
        }, 
        "1": {
            "acid": 0.5, 
            "folate": 0.5
        }, 
        "1.": {
            "HISTORY:": 0.5, 
            "ISSUE:": 0.5
        }, 
        "1.6.": {
            "to": 1.0
        }, 
        "1.8": {
            "of": 1.0
        }, 
        "1.8.": {
            "is": 1.0
        }, 
        "10": {
            "take": 1.0
        }, 
        "10/21/2006": {
            "Date:": 1.0
        }, 
        "1000.": {
            "of": 1.0
        }, 
        "1064": {
            "of": 1.0
        }, 
        "11/23/2006": {
            "|": 1.0
        }, 
        "117.7": {
            "Weight": 1.0
        }, 
        "12": {
            "Novolog": 0.6666666666666666, 
            "take": 0.3333333333333333
        }, 
        "1243403": {
            "|": 1.0
        }, 
        "1250": {
            "carbonate": 1.0
        }, 
        "12:00:00": {
            "11/23/2006": 1.0
        }, 
        "130": {
            "sodium": 1.0
        }, 
        "14": {
            "Novolog": 1.0
        }, 
        "140/82": {
            "pressure": 1.0
        }, 
        "15-pound": {
            "a": 1.0
        }, 
        "150": {
            "Neoral": 0.2, 
            "Synthroid": 0.4, 
            "cyclosporin": 0.4
        }, 
        "150-200": {
            "is": 1.0
        }, 
        "1500": {
            "CellCept": 1.0
        }, 
        "1886546": {
            "ID": 1.0
        }, 
        "2.": {
            "discharge.": 0.5, 
            "placement.": 0.5
        }, 
        "2.2": {
            "creatinine": 0.5, 
            "of": 0.5
        }, 
        "2.5": {
            "methotrexate": 1.0
        }, 
        "2/6": {
            ",": 1.0
        }, 
        "20": {
            "K-dur": 0.3333333333333333, 
            "Pravachol": 0.3333333333333333, 
            "Pravastatin": 0.3333333333333333
        }, 
        "2002": {
            "in": 1.0
        }, 
        "201-250": {
            "is": 1.0
        }, 
        "251-300": {
            "is": 1.0
        }, 
        "3.": {
            "discharge.": 0.5, 
            "insufficiency.": 0.5
        }, 
        "3/26/2006": {
            "Date:": 1.0
        }, 
        "300": {
            "XT": 0.5, 
            "release": 0.5
        }, 
        "301-350": {
            "is": 1.0
        }, 
        "350-400": {
            "is": 1.0
        }, 
        "4": {
            "take": 1.0
        }, 
        "4.": {
            "Hypothyroidism.": 0.5, 
            "colchicine.": 0.5
        }, 
        "4.9.": {
            "potassium": 1.0
        }, 
        "40": {
            ")": 0.5, 
            "Torsemide": 0.5
        }, 
        "400": {
            "E": 0.3333333333333333, 
            "oxide": 0.3333333333333333, 
            "than": 0.3333333333333333
        }, 
        "41614963": {
            "|": 1.0
        }, 
        "420": {
            "oxide": 1.0
        }, 
        "45-year-old": {
            "A": 1.0
        }, 
        "5-0284099": {
            "document:": 1.0
        }, 
        "5.": {
            "regurgitation.": 1.0
        }, 
        "500": {
            "C": 0.5, 
            "carbonate": 0.5
        }, 
        "6": {
            "take": 1.0
        }, 
        "6.": {
            "pancreatitis.": 1.0
        }, 
        "626012950": {
            "": 1.0
        }, 
        "7": {
            "prednisone": 1.0
        }, 
        "7.5": {
            "prednisone": 1.0
        }, 
        "8": {
            "take": 1.0
        }, 
        "8/13/06": {
            "D:": 1.0
        }, 
        "87": {
            "at": 1.0
        }, 
        "92": {
            "rate": 1.0
        }, 
        "97%": {
            "is": 1.0
        }, 
        "98.8.": {
            "temperature": 1.0
        }, 
        "A": {
            "ILLNESS:": 1.0
        }, 
        "ADMISSION:": {
            "ON": 1.0
        }, 
        "ADMISSIONS": {
            "edema.": 1.0
        }, 
        "AICD": {
            "and": 1.0
        }, 
        "ALLERGIES:": {
            "b.i.d.": 1.0
        }, 
        "AM": {
            "12:00:00": 1.0
        }, 
        "ATTENDING:": {
            "3/26/2006": 1.0
        }, 
        "Admission": {
            "|": 1.0
        }, 
        "At": {
            "dry.": 1.0
        }, 
        "Attending:": {
            "DAMION": 1.0
        }, 
        "BRAYE": {
            "By:": 1.0
        }, 
        "BY": {
            "COURSE": 1.0
        }, 
        "Baseline": {
            "related.": 1.0
        }, 
        "Blood": {
            "98.8.": 1.0
        }, 
        "By:": {
            "Dictated": 1.0
        }, 
        "C": {
            "Vitamin": 1.0
        }, 
        "COURSE": {
            "HOSPITAL": 1.0
        }, 
        "Calcium": {
            "ADMISSION:": 1.0
        }, 
        "Cardiomyopathy": {
            "1.": 1.0
        }, 
        "Cardiovascular": {
            "kilograms.": 1.0
        }, 
        "Cardiovascular:": {
            "2.": 1.0
        }, 
        "Cartia": {
            ",": 1.0
        }, 
        "CellCept": {
            ",": 1.0
        }, 
        "Chronic": {
            "2.": 1.0
        }, 
        "Creatinine": {
            "1.8.": 0.5, 
            "failure.": 0.5
        }, 
        "D:": {
            "1886546": 1.0
        }, 
        "DAMION": {
            ",": 1.0
        }, 
        "DIABETES": {
            "ONSET": 1.0
        }, 
        "DIAGNOSIS:": {
            "M.D.": 1.0
        }, 
        "DIS": {
            "|": 1.0
        }, 
        "DISCHARGE": {
            "1.6.": 1.0
        }, 
        "Date:": {
            "Admission": 0.5, 
            "Discharge": 0.5
        }, 
        "Dictated": {
            "HFFocus": 1.0
        }, 
        "Dictation": {
            "JUSTIN": 1.0
        }, 
        "Discharge": {
            "Unsigned": 1.0
        }, 
        "Dr.": {
            "with": 1.0
        }, 
        "E": {
            "Vitamin": 1.0
        }, 
        "EKG": {
            "4.9.": 1.0
        }, 
        "EKGs.": {
            "prior": 1.0
        }, 
        "EXAMINATION": {
            "PHYSICAL": 1.0
        }, 
        "Endocrine": {
            "diabetes.": 1.0
        }, 
        "Endocrine:": {
            "1.": 1.0
        }, 
        "Glargine": {
            "(": 1.0
        }, 
        "Gout.": {
            "6.": 1.0
        }, 
        "HFFocus": {
            "5-0284099": 1.0
        }, 
        "HISTORY": {
            "diabetes": 1.0
        }, 
        "HISTORY:": {
            "MEDICAL": 1.0
        }, 
        "HOSPITAL": {
            "EKGs.": 1.0
        }, 
        "History": {
            "5.": 1.0
        }, 
        "Hypothyroidism.": {
            "3.": 1.0
        }, 
        "ID": {
            "Dictation": 1.0
        }, 
        "ILLNESS:": {
            "PRESENT": 1.0
        }, 
        "ISSUE:": {
            "BY": 1.0
        }, 
        "If": {
            "follows:": 1.0
        }, 
        "JUSTIN": {
            ",": 1.0
        }, 
        "Jonson": {
            "Dr.": 1.0
        }, 
        "K-dur": {
            ",": 1.0
        }, 
        "LABORATORIES:": {
            "ADMISSIONS": 1.0
        }, 
        "Lantus": {
            ",": 0.5, 
            "of": 0.5
        }, 
        "M.D.": {
            "RAFAEL": 1.0
        }, 
        "MEDICAL": {
            "PAST": 1.0
        }, 
        "MEDICATIONS": {
            "Gout.": 1.0
        }, 
        "MEDICATIONS:": {
            "DISCHARGE": 1.0
        }, 
        "Mettee": {
            "Napoleon": 1.0
        }, 
        "NEW": {
            "|": 1.0
        }, 
        "Napoleon": {
            "with": 1.0
        }, 
        "Neoral": {
            ",": 1.0
        }, 
        "New-onset": {
            "DIAGNOSIS:": 1.0
        }, 
        "No": {
            "border.": 1.0
        }, 
        "Notable": {
            "ADMISSION:": 0.5, 
            "LABORATORIES:": 0.5
        }, 
        "Novolog": {
            ",": 0.6666666666666666, 
            "a": 0.16666666666666666, 
            "and": 0.16666666666666666
        }, 
        "OF": {
            "HISTORY": 1.0
        }, 
        "ON": {
            "EXAMINATION": 0.5, 
            "MEDICATIONS": 0.5
        }, 
        "ONSET": {
            "NEW": 1.0
        }, 
        "PAST": {
            "negative.": 1.0
        }, 
        "PCP": {
            "his": 1.0
        }, 
        "PHYSICAL": {
            "\"shaking.\"": 1.0
        }, 
        "PRESENT": {
            "OF": 1.0
        }, 
        "Penicillin": {
            "ALLERGIES:": 1.0
        }, 
        "Pravachol": {
            ",": 1.0
        }, 
        "Pravastatin": {
            ",": 1.0
        }, 
        "RAFAEL": {
            ",": 1.0
        }, 
        "RM": {
            "|": 1.0
        }, 
        "Regular": {
            "examination:": 1.0
        }, 
        "Renal:": {
            "4.": 1.0
        }, 
        "Report": {
            "10/21/2006": 1.0
        }, 
        "Rheumatology:": {
            "3.": 1.0
        }, 
        "Rocaltrol": {
            ",": 1.0
        }, 
        "SPIESS": {
            "ATTENDING:": 1.0
        }, 
        "Soft": {
            "rhythm.": 1.0
        }, 
        "Status:": {
            "Report": 1.0
        }, 
        "Synthroid": {
            ",": 1.0
        }, 
        "T": {
            "anterior": 1.0
        }, 
        "T:": {
            "8/13/06": 1.0
        }, 
        "The": {
            "1000.": 0.1111111111111111, 
            "Cardiovascular:": 0.1111111111111111, 
            "Endocrine:": 0.1111111111111111, 
            "Renal:": 0.1111111111111111, 
            "Rheumatology:": 0.1111111111111111, 
            "a.c.": 0.1111111111111111, 
            "air.": 0.1111111111111111, 
            "medications.": 0.1111111111111111, 
            "scale.": 0.1111111111111111
        }, 
        "Torsemide": {
            ",": 1.0
        }, 
        "Tricuspid": {
            "4.": 1.0
        }, 
        "Unsigned": {
            "Status:": 0.5, 
            "|": 0.5
        }, 
        "VIDA": {
            "Attending:": 1.0
        }, 
        "VNA": {
            "with": 1.0
        }, 
        "Vitamin": {
            ",": 0.75, 
            "MEDICATIONS:": 0.25
        }, 
        "Was": {
            "edema.": 1.0
        }, 
        "Weight": {
            "appearing.": 1.0
        }, 
        "XT": {
            "Cartia": 1.0
        }, 
        "a": {
            "approximately": 0.14285714285714285, 
            "for": 0.14285714285714285, 
            "from": 0.14285714285714285, 
            "have": 0.14285714285714285, 
            "with": 0.42857142857142855
        }, 
        "a.c.": {
            "q.": 1.0
        }, 
        "acid": {
            "folic": 1.0
        }, 
        "acute": {
            "mild": 0.5, 
            "prerenal": 0.5
        }, 
        "administration": {
            "insulin": 1.0
        }, 
        "admission": {
            "at": 0.25, 
            "during": 0.25, 
            "of": 0.5
        }, 
        "aggressively": {
            "was": 1.0
        }, 
        "air.": {
            "room": 1.0
        }, 
        "also": {
            "patient": 1.0
        }, 
        "and": {
            ",": 0.3125, 
            "admission": 0.0625, 
            "cardiomyopathy": 0.0625, 
            "clinic": 0.0625, 
            "consulted": 0.0625, 
            "hydrated": 0.0625, 
            "myalgias": 0.0625, 
            "nurse": 0.0625, 
            "rate": 0.0625, 
            "testing": 0.0625, 
            "throat": 0.0625, 
            "transplant": 0.0625
        }, 
        "anterior": {
            "and": 1.0
        }, 
        "appearing.": {
            "well": 1.0
        }, 
        "approximately": {
            "reported": 1.0
        }, 
        "are": {
            "that": 1.0
        }, 
        "as": {
            "is": 1.0
        }, 
        "assist": {
            "to": 1.0
        }, 
        "at": {
            "Creatinine": 0.4, 
            "best": 0.2, 
            "mg": 0.2, 
            "rhythm": 0.2
        }, 
        "atrial": {
            "left": 1.0
        }, 
        "b.i.d.": {
            "mg": 0.8888888888888888, 
            "p.o.": 0.1111111111111111
        }, 
        "baseline": {
            "a": 1.0
        }, 
        "beats": {
            "87": 1.0
        }, 
        "before": {
            "units": 1.0
        }, 
        "best": {
            "heard": 1.0
        }, 
        "block": {
            "bundle-branch": 1.0
        }, 
        "blood": {
            "If": 0.14285714285714285, 
            "a": 0.14285714285714285, 
            "if": 0.5714285714285714, 
            "of": 0.14285714285714285
        }, 
        "blurry": {
            ",": 1.0
        }, 
        "border.": {
            "sternal": 1.0
        }, 
        "breakfast": {
            "before": 1.0
        }, 
        "bundle-branch": {
            "right": 1.0
        }, 
        "but": {
            ",": 1.0
        }, 
        "by": {
            "seen": 1.0
        }, 
        "calcium": {
            ",": 1.0
        }, 
        "call": {
            "to": 1.0
        }, 
        "carbonate": {
            "Calcium": 0.5, 
            "calcium": 0.5
        }, 
        "cardiac": {
            "post": 1.0
        }, 
        "cardiomyopathy": {
            "familial": 1.0
        }, 
        "changes": {
            "wave": 1.0
        }, 
        "chronic": {
            "and": 0.5, 
            "with": 0.5
        }, 
        "clinic": {
            "diabetes": 1.0
        }, 
        "colchicine": {
            ",": 1.0
        }, 
        "colchicine.": {
            "on": 1.0
        }, 
        "combination": {
            "a": 1.0
        }, 
        "combined": {
            ",": 1.0
        }, 
        "consulted": {
            "was": 1.0
        }, 
        "controlled": {
            "was": 1.0
        }, 
        "cough": {
            "and": 1.0
        }, 
        "cramps": {
            "muscle": 1.0
        }, 
        "creatinine": {
            ",": 0.5, 
            "Baseline": 0.5
        }, 
        "cyclosporin": {
            ",": 0.5, 
            "and": 0.5
        }, 
        "daily": {
            "mcg": 0.2, 
            "mg": 0.7333333333333333, 
            "units": 0.06666666666666667
        }, 
        "day": {
            "the": 1.0
        }, 
        "days": {
            "several": 1.0
        }, 
        "decrease": {
            "with": 1.0
        }, 
        "demonstrated": {
            "patient": 1.0
        }, 
        "diabetes": {
            "New-onset": 0.5, 
            "the": 0.5
        }, 
        "diabetes.": {
            "new-onset": 1.0
        }, 
        "diabetic": {
            "the": 1.0
        }, 
        "diltiazem": {
            "is": 1.0
        }, 
        "dinner": {
            "before": 1.0
        }, 
        "discharge": {
            "at": 1.0
        }, 
        "discharge.": {
            "to": 1.0
        }, 
        "discharged": {
            "was": 1.0
        }, 
        "doctor.": {
            "his": 1.0
        }, 
        "document:": {
            "eScription": 1.0
        }, 
        "dry.": {
            "intravascularly": 1.0
        }, 
        "during": {
            "flare": 1.0
        }, 
        "eScription": {
            "doctor.": 1.0
        }, 
        "edema.": {
            "extremity": 1.0
        }, 
        "enlargement": {
            "atrial": 1.0
        }, 
        "euvolemic": {
            "and": 1.0
        }, 
        "evidence": {
            ",": 1.0
        }, 
        "examination:": {
            "Cardiovascular": 1.0
        }, 
        "extended": {
            "diltiazem": 1.0
        }, 
        "extremity": {
            "lower": 1.0
        }, 
        "failure.": {
            "renal": 1.0
        }, 
        "familial": {
            "of": 1.0
        }, 
        "fingerstick": {
            "a": 1.0
        }, 
        "flare": {
            "gout": 1.0
        }, 
        "folate": {
            ",": 1.0
        }, 
        "folic": {
            ",": 1.0
        }, 
        "follows:": {
            "as": 1.0
        }, 
        "followup": {
            "with": 1.0
        }, 
        "for": {
            "Notable": 0.6666666666666666, 
            "admission": 0.3333333333333333
        }, 
        "found": {
            "and": 1.0
        }, 
        "from": {
            "2.2": 0.5, 
            "unchanged": 0.5
        }, 
        "glucose": {
            "blood": 1.0
        }, 
        "gout": {
            "acute": 1.0
        }, 
        "greater": {
            "is": 0.5, 
            "with": 0.5
        }, 
        "had": {
            "discharge": 0.5, 
            "patient": 0.5
        }, 
        "have": {
            "to": 1.0
        }, 
        "he": {
            ",": 0.5, 
            "which": 0.5
        }, 
        "heard": {
            "murmur": 1.0
        }, 
        "heart": {
            ",": 1.0
        }, 
        "his": {
            "by": 0.5, 
            "call": 0.5
        }, 
        "history": {
            "a": 1.0
        }, 
        "home": {
            "with": 1.0
        }, 
        "hydrated": {
            "aggressively": 1.0
        }, 
        "if": {
            ",": 1.0
        }, 
        "immunosuppression": {
            ",": 1.0
        }, 
        "in": {
            "Jonson": 0.3333333333333333, 
            "decrease": 0.3333333333333333, 
            "transplant": 0.3333333333333333
        }, 
        "incomplete": {
            ",": 1.0
        }, 
        "instructed": {
            "is": 1.0
        }, 
        "insufficiency": {
            "renal": 1.0
        }, 
        "insufficiency.": {
            "renal": 1.0
        }, 
        "insulin": {
            "Lantus": 0.5, 
            "and": 0.5
        }, 
        "intravascularly": {
            "was": 1.0
        }, 
        "is": {
            "creatinine": 0.07692307692307693, 
            "it": 0.07692307692307693, 
            "patient": 0.15384615384615385, 
            "saturation": 0.07692307692307693, 
            "scale": 0.07692307692307693, 
            "sugar": 0.38461538461538464, 
            "systems": 0.07692307692307693, 
            "that": 0.07692307692307693
        }, 
        "it": {
            "if": 1.0
        }, 
        "kilograms.": {
            "117.7": 1.0
        }, 
        "leads": {
            "Penicillin": 1.0
        }, 
        "left": {
            "of": 0.5, 
            "the": 0.5
        }, 
        "likely": {
            ",": 0.5, 
            "2.2": 0.5
        }, 
        "loss": {
            "weight": 1.0
        }, 
        "lower": {
            "No": 0.5, 
            "usual": 0.5
        }, 
        "lunch": {
            "before": 1.0
        }, 
        "magnesium": {
            ",": 1.0
        }, 
        "man": {
            "45-year-old": 1.0
        }, 
        "mcg": {
            "0.25": 0.3333333333333333, 
            "150": 0.6666666666666666
        }, 
        "medication": {
            "immunosuppression": 1.0
        }, 
        "medications.": {
            "home": 1.0
        }, 
        "methotrexate": {
            ",": 1.0
        }, 
        "mg": {
            "0.25": 0.04, 
            "0.3": 0.04, 
            "0.6": 0.04, 
            "1": 0.08, 
            "1250": 0.04, 
            "150": 0.12, 
            "1500": 0.08, 
            "2.5": 0.04, 
            "20": 0.12, 
            "201-250": 0.04, 
            "300": 0.08, 
            "40": 0.04, 
            "400": 0.04, 
            "420": 0.04, 
            "500": 0.08, 
            "7": 0.04, 
            "7.5": 0.04
        }, 
        "mild": {
            "had": 1.0
        }, 
        "minute": {
            "per": 1.0
        }, 
        "murmur": {
            "systolic": 1.0
        }, 
        "muscle": {
            ",": 1.0
        }, 
        "myalgias": {
            "and": 1.0
        }, 
        "negative.": {
            "is": 1.0
        }, 
        "new-onset": {
            "with": 1.0
        }, 
        "night": {
            "at": 1.0
        }, 
        "normal": {
            "EKG": 1.0
        }, 
        "normalized": {
            "had": 1.0
        }, 
        "nurse": {
            "teaching": 1.0
        }, 
        "of": {
            "History": 0.07692307692307693, 
            "admission": 0.07692307692307693, 
            "baseline": 0.07692307692307693, 
            "day": 0.07692307692307693, 
            "evidence": 0.07692307692307693, 
            "fingerstick": 0.07692307692307693, 
            "glucose": 0.07692307692307693, 
            "history": 0.07692307692307693, 
            "regimen": 0.07692307692307693, 
            "review": 0.07692307692307693, 
            "time": 0.07692307692307693, 
            "understanding": 0.07692307692307693, 
            "weeks": 0.07692307692307693
        }, 
        "on": {
            "97%": 0.3333333333333333, 
            "PCP": 0.3333333333333333, 
            "started": 0.3333333333333333
        }, 
        "otherwise": {
            "but": 1.0
        }, 
        "over": {
            "loss": 1.0
        }, 
        "oxide": {
            "magnesium": 1.0
        }, 
        "p.o.": {
            "mg": 1.0
        }, 
        "p.r.n.": {
            "daily": 1.0
        }, 
        "pancreatitis.": {
            "of": 1.0
        }, 
        "patient": {
            "The": 0.8, 
            "the": 0.2
        }, 
        "per": {
            "beats": 1.0
        }, 
        "placement.": {
            "AICD": 1.0
        }, 
        "polydipsia": {
            ",": 1.0
        }, 
        "polyuria": {
            "of": 1.0
        }, 
        "post": {
            "status": 1.0
        }, 
        "potassium": {
            ",": 1.0
        }, 
        "prednisone": {
            ",": 1.0
        }, 
        "prerenal": {
            "to": 1.0
        }, 
        "presented": {
            "insufficiency": 1.0
        }, 
        "pressure": {
            "Blood": 1.0
        }, 
        "prior": {
            "administration": 0.3333333333333333, 
            "euvolemic": 0.3333333333333333, 
            "from": 0.3333333333333333
        }, 
        "proper": {
            "demonstrated": 1.0
        }, 
        "q.": {
            "Novolog": 0.5, 
            "scale": 0.5
        }, 
        "q.a.m.": {
            "mg": 0.5, 
            "subcutaneous": 0.5
        }, 
        "rate": {
            "Regular": 0.5, 
            "heart": 0.5
        }, 
        "regimen": {
            "combination": 1.0
        }, 
        "regurgitation.": {
            "Tricuspid": 1.0
        }, 
        "related": {
            "likely": 1.0
        }, 
        "related.": {
            "medication": 1.0
        }, 
        "release": {
            "extended": 1.0
        }, 
        "renal": {
            "Chronic": 0.25, 
            "acute": 0.25, 
            "chronic": 0.5
        }, 
        "reported": {
            "also": 0.5, 
            "and": 0.5
        }, 
        "review": {
            "otherwise": 1.0
        }, 
        "rhythm": {
            "sinus": 1.0
        }, 
        "rhythm.": {
            "and": 1.0
        }, 
        "right": {
            "incomplete": 1.0
        }, 
        "room": {
            "on": 1.0
        }, 
        "saturation": {
            ",": 1.0
        }, 
        "scale": {
            "sliding": 1.0
        }, 
        "scale.": {
            "sliding": 1.0
        }, 
        "seen": {
            "Was": 1.0
        }, 
        "service": {
            "Endocrine": 1.0
        }, 
        "services": {
            "VNA": 1.0
        }, 
        "several": {
            "times": 1.0
        }, 
        "sinus": {
            "normal": 1.0
        }, 
        "sliding": {
            "Novolog": 0.6666666666666666, 
            "The": 0.3333333333333333
        }, 
        "sodium": {
            ",": 1.0
        }, 
        "sore": {
            "reported": 1.0
        }, 
        "started": {
            "was": 1.0
        }, 
        "status": {
            ",": 0.5, 
            "and": 0.5
        }, 
        "sternal": {
            "left": 1.0
        }, 
        "subcutaneous": {
            "units": 1.0
        }, 
        "sugar": {
            "blood": 1.0
        }, 
        "systems": {
            "of": 1.0
        }, 
        "systolic": {
            "2/6": 1.0
        }, 
        "t.i.d.": {
            "mg": 1.0
        }, 
        "take": {
            "150-200": 0.2, 
            "251-300": 0.2, 
            "301-350": 0.2, 
            "350-400": 0.2, 
            "mg": 0.2
        }, 
        "teaching": {
            "diabetic": 1.0
        }, 
        "temperature": {
            "for": 1.0
        }, 
        "testing": {
            "glucose": 1.0
        }, 
        "than": {
            "greater": 1.0
        }, 
        "that": {
            "XT": 0.5, 
            "changes": 0.5
        }, 
        "the": {
            ",": 0.2857142857142857, 
            "At": 0.14285714285714285, 
            "and": 0.14285714285714285, 
            "at": 0.14285714285714285, 
            "in": 0.14285714285714285, 
            "on": 0.14285714285714285
        }, 
        "three": {
            "over": 1.0
        }, 
        "throat": {
            "sore": 1.0
        }, 
        "time": {
            "the": 1.0
        }, 
        "times": {
            "cough": 1.0
        }, 
        "to": {
            "found": 0.125, 
            "instructed": 0.125, 
            "leads": 0.125, 
            "normalized": 0.125, 
            "prior": 0.25, 
            "related": 0.125, 
            "services": 0.125
        }, 
        "transplant": {
            "cardiac": 0.3333333333333333, 
            "likely": 0.3333333333333333, 
            "post": 0.3333333333333333
        }, 
        "two": {
            "than": 1.0
        }, 
        "unchanged": {
            "are": 1.0
        }, 
        "understanding": {
            "proper": 1.0
        }, 
        "units": {
            "10": 0.1, 
            "12": 0.3, 
            "14": 0.1, 
            "4": 0.1, 
            "40": 0.1, 
            "400": 0.1, 
            "6": 0.1, 
            "8": 0.1
        }, 
        "usual": {
            "in": 1.0
        }, 
        "vision": {
            "blurry": 1.0
        }, 
        "was": {
            "he": 0.3333333333333333, 
            "patient": 0.5, 
            "service": 0.16666666666666666
        }, 
        "wave": {
            "T": 1.0
        }, 
        "weeks": {
            "three": 0.5, 
            "two": 0.5
        }, 
        "weight": {
            "15-pound": 1.0
        }, 
        "well": {
            "but": 1.0
        }, 
        "which": {
            "for": 1.0
        }, 
        "with": {
            "and": 0.16666666666666666, 
            "assist": 0.08333333333333333, 
            "combined": 0.08333333333333333, 
            "controlled": 0.08333333333333333, 
            "discharged": 0.08333333333333333, 
            "followup": 0.08333333333333333, 
            "man": 0.08333333333333333, 
            "patient": 0.16666666666666666, 
            "presented": 0.08333333333333333, 
            "weeks": 0.08333333333333333
        }, 
        "|": {
            "1243403": 0.1111111111111111, 
            "41614963": 0.1111111111111111, 
            "626012950": 0.1111111111111111, 
            "AM": 0.1111111111111111, 
            "DIABETES": 0.1111111111111111, 
            "DIS": 0.1111111111111111, 
            "RM": 0.1111111111111111, 
            "Unsigned": 0.1111111111111111, 
            "|": 0.1111111111111111
        }
    }, 
    "id": "316", 
    "text": " 626012950 | RM | 41614963 | | 1243403 | 11/23/2006 12:00:00 AM | NEW ONSET DIABETES | Unsigned | DIS | Admission Date: 10/21/2006 Report Status: Unsigned Discharge Date: 3/26/2006 ATTENDING: SPIESS , RAFAEL M.D. DIAGNOSIS: New-onset diabetes HISTORY OF PRESENT ILLNESS: A 45-year-old man with a history of familial cardiomyopathy and status post cardiac transplant in 2002 , and chronic renal insufficiency presented with greater than two weeks of polyuria , polydipsia , blurry vision , muscle cramps , and myalgias and reported approximately a 15-pound weight loss over three weeks with decrease in usual lower extremity edema. Was seen by his PCP on the day of admission and found to have a fingerstick of 1000. The patient also reported sore throat and cough times several days , but otherwise review of systems is negative. PAST MEDICAL HISTORY: 1. Cardiomyopathy , status post transplant and AICD placement. 2. Chronic renal insufficiency. 3. Hypothyroidism. 4. Tricuspid regurgitation. 5. History of pancreatitis. 6. Gout. MEDICATIONS ON ADMISSION: Calcium carbonate 1250 mg t.i.d. , Cartia XT 300 mg daily , CellCept 1500 mg b.i.d. , colchicine 0.6 mg daily p.r.n. , Neoral 150 mg b.i.d. , folate 1 mg daily , K-dur 20 mg daily , magnesium oxide 400 mg b.i.d. , methotrexate 2.5 mg daily , Pravastatin 20 mg daily , prednisone 7 mg daily , Rocaltrol 0.25 mg daily , Synthroid 150 mcg daily , Torsemide 40 mg daily , Vitamin C , Vitamin E , and cyclosporin 150 mg b.i.d. ALLERGIES: Penicillin leads to \"shaking.\" PHYSICAL EXAMINATION ON ADMISSION: Notable for temperature 98.8. Blood pressure 140/82 , heart rate 92 , saturation is 97% on room air. The patient is #obese# , but well appearing. Weight 117.7 kilograms. Cardiovascular examination: Regular rate and rhythm. Soft , 2/6 systolic murmur heard best at the left sternal border. No lower extremity edema. ADMISSIONS LABORATORIES: Notable for a blood glucose of 1064 , creatinine 2.2 from a baseline of 1.8 , sodium 130 , potassium 4.9. EKG normal sinus rhythm at 87 beats per minute , evidence of left atrial enlargement , incomplete right bundle-branch block , and anterior T wave changes that are unchanged from prior EKGs. HOSPITAL COURSE BY ISSUE: 1. Endocrine: The patient with new-onset diabetes. Endocrine service was consulted and the patient was controlled with a combination regimen of Lantus , Novolog q. a.c. , combined with a Novolog sliding scale. The patient was discharged with followup with Napoleon Mettee , the diabetic teaching nurse and with Dr. Jonson in the diabetes clinic and with VNA services to assist with home medications. The patient demonstrated proper understanding of blood glucose testing and insulin administration prior to discharge. 2. Cardiovascular: The patient was intravascularly dry. At the time of admission , he was aggressively hydrated and euvolemic prior to discharge. 3. Rheumatology: The patient had mild acute gout flare during admission for which he was started on colchicine. 4. Renal: The patient with chronic renal insufficiency , likely transplant , immunosuppression medication related. Baseline creatinine is 1.8. Creatinine at admission of 2.2 likely related to prerenal acute renal failure. Creatinine at discharge had normalized to 1.6. DISCHARGE MEDICATIONS: Vitamin C 500 mg b.i.d. , Rocaltrol 0.25 mcg daily , calcium carbonate 500 mg t.i.d. , colchicine 0.3 mg p.o. b.i.d. , cyclosporin 150 mg b.i.d. , folic acid 1 mg daily , Synthroid 150 mcg daily , magnesium oxide 420 mg b.i.d. , prednisone 7.5 mg q.a.m. , Vitamin E 400 units daily , Pravachol 20 mg at night , Cartia XT that is diltiazem extended release 300 mg daily , CellCept 1500 mg b.i.d. , Lantus insulin ( Glargine ) 40 units subcutaneous q.a.m. , Novolog 12 units before breakfast , Novolog 12 units before lunch , Novolog 14 units before dinner , and Novolog sliding scale q. a.c. The sliding scale is as follows: If blood sugar is 150-200 take 4 units , if blood sugar is 201-250 mg take 6 units , if blood sugar is 251-300 take 8 units , if blood sugar is 301-350 take 10 units , if blood sugar is 350-400 take 12 units , if it is greater than 400 , the patient is instructed to call his doctor. eScription document: 5-0284099 HFFocus Dictated By: BRAYE , DAMION Attending: VIDA , JUSTIN Dictation ID 1886546 D: 8/13/06 T: 8/13/06", 
    "tri": {
        "\"shaking.\"": {
            "leads~to": 1.0
        }, 
        "#obese#": {
            "patient~is": 1.0
        }, 
        "(": {
            "Lantus~insulin": 1.0
        }, 
        ")": {
            "(~Glargine": 1.0
        }, 
        ",": {
            ",~polydipsia": 0.015384615384615385, 
            "1.~Cardiomyopathy": 0.015384615384615385, 
            "10~units": 0.015384615384615385, 
            "12~units": 0.015384615384615385, 
            "4~units": 0.015384615384615385, 
            "6~units": 0.015384615384615385, 
            "8~units": 0.015384615384615385, 
            "ATTENDING:~SPIESS": 0.015384615384615385, 
            "Attending:~VIDA": 0.015384615384615385, 
            "By:~BRAYE": 0.015384615384615385, 
            "Napoleon~Mettee": 0.015384615384615385, 
            "Vitamin~C": 0.015384615384615385, 
            "Vitamin~E": 0.015384615384615385, 
            "atrial~enlargement": 0.015384615384615385, 
            "at~night": 0.015384615384615385, 
            "before~breakfast": 0.015384615384615385, 
            "before~dinner": 0.015384615384615385, 
            "before~lunch": 0.015384615384615385, 
            "blurry~vision": 0.015384615384615385, 
            "bundle-branch~block": 0.015384615384615385, 
            "daily~p.r.n.": 0.015384615384615385, 
            "in~2002": 0.015384615384615385, 
            "is~#obese#": 0.015384615384615385, 
            "likely~transplant": 0.015384615384615385, 
            "mcg~daily": 0.046153846153846156, 
            "mg~b.i.d.": 0.1076923076923077, 
            "mg~daily": 0.15384615384615385, 
            "mg~q.a.m.": 0.015384615384615385, 
            "mg~t.i.d.": 0.03076923076923077, 
            "muscle~cramps": 0.015384615384615385, 
            "of~1.8": 0.015384615384615385, 
            "of~1064": 0.015384615384615385, 
            "of~Lantus": 0.015384615384615385, 
            "of~admission": 0.015384615384615385, 
            "of~polyuria": 0.015384615384615385, 
            "p.o.~b.i.d.": 0.015384615384615385, 
            "per~minute": 0.015384615384615385, 
            "pressure~140/82": 0.015384615384615385, 
            "q.~a.c.": 0.015384615384615385, 
            "rate~92": 0.015384615384615385, 
            "renal~insufficiency": 0.015384615384615385, 
            "rhythm.~Soft": 0.015384615384615385, 
            "several~days": 0.015384615384615385, 
            "sodium~130": 0.015384615384615385, 
            "subcutaneous~q.a.m.": 0.015384615384615385, 
            "than~400": 0.015384615384615385, 
            "units~daily": 0.015384615384615385
        }, 
        "0.25": {
            ",~Rocaltrol": 1.0
        }, 
        "0.3": {
            ",~colchicine": 1.0
        }, 
        "0.6": {
            ",~colchicine": 1.0
        }, 
        "1": {
            ",~folate": 0.5, 
            "folic~acid": 0.5
        }, 
        "1.": {
            "BY~ISSUE:": 0.5, 
            "MEDICAL~HISTORY:": 0.5
        }, 
        "1.6.": {
            "normalized~to": 1.0
        }, 
        "1.8": {
            "baseline~of": 1.0
        }, 
        "1.8.": {
            "creatinine~is": 1.0
        }, 
        "10": {
            "301-350~take": 1.0
        }, 
        "10/21/2006": {
            "Admission~Date:": 1.0
        }, 
        "1000.": {
            "fingerstick~of": 1.0
        }, 
        "1064": {
            "glucose~of": 1.0
        }, 
        "11/23/2006": {
            "1243403~|": 1.0
        }, 
        "117.7": {
            "appearing.~Weight": 1.0
        }, 
        "12": {
            ",~Novolog": 0.6666666666666666, 
            "350-400~take": 0.3333333333333333
        }, 
        "1243403": {
            "|~|": 1.0
        }, 
        "1250": {
            "Calcium~carbonate": 1.0
        }, 
        "12:00:00": {
            "|~11/23/2006": 1.0
        }, 
        "130": {
            ",~sodium": 1.0
        }, 
        "14": {
            ",~Novolog": 1.0
        }, 
        "140/82": {
            "Blood~pressure": 1.0
        }, 
        "15-pound": {
            "approximately~a": 1.0
        }, 
        "150": {
            ",~Neoral": 0.2, 
            ",~Synthroid": 0.4, 
            ",~cyclosporin": 0.2, 
            "and~cyclosporin": 0.2
        }, 
        "150-200": {
            "sugar~is": 1.0
        }, 
        "1500": {
            ",~CellCept": 1.0
        }, 
        "1886546": {
            "Dictation~ID": 1.0
        }, 
        "2.": {
            "AICD~placement.": 0.5, 
            "to~discharge.": 0.5
        }, 
        "2.2": {
            ",~creatinine": 0.5, 
            "admission~of": 0.5
        }, 
        "2.5": {
            ",~methotrexate": 1.0
        }, 
        "2/6": {
            "Soft~,": 1.0
        }, 
        "20": {
            ",~K-dur": 0.3333333333333333, 
            ",~Pravachol": 0.3333333333333333, 
            ",~Pravastatin": 0.3333333333333333
        }, 
        "2002": {
            "transplant~in": 1.0
        }, 
        "201-250": {
            "sugar~is": 1.0
        }, 
        "251-300": {
            "sugar~is": 1.0
        }, 
        "3.": {
            "renal~insufficiency.": 0.5, 
            "to~discharge.": 0.5
        }, 
        "3/26/2006": {
            "Discharge~Date:": 1.0
        }, 
        "300": {
            "Cartia~XT": 0.5, 
            "extended~release": 0.5
        }, 
        "301-350": {
            "sugar~is": 1.0
        }, 
        "350-400": {
            "sugar~is": 1.0
        }, 
        "4": {
            "150-200~take": 1.0
        }, 
        "4.": {
            "3.~Hypothyroidism.": 0.5, 
            "on~colchicine.": 0.5
        }, 
        "4.9.": {
            ",~potassium": 1.0
        }, 
        "40": {
            ",~Torsemide": 0.5, 
            "Glargine~)": 0.5
        }, 
        "400": {
            "Vitamin~E": 0.3333333333333333, 
            "greater~than": 0.3333333333333333, 
            "magnesium~oxide": 0.3333333333333333
        }, 
        "41614963": {
            "RM~|": 1.0
        }, 
        "420": {
            "magnesium~oxide": 1.0
        }, 
        "45-year-old": {
            "ILLNESS:~A": 1.0
        }, 
        "5-0284099": {
            "eScription~document:": 1.0
        }, 
        "5.": {
            "Tricuspid~regurgitation.": 1.0
        }, 
        "500": {
            "Vitamin~C": 0.5, 
            "calcium~carbonate": 0.5
        }, 
        "6": {
            "mg~take": 1.0
        }, 
        "6.": {
            "of~pancreatitis.": 1.0
        }, 
        "7": {
            ",~prednisone": 1.0
        }, 
        "7.5": {
            ",~prednisone": 1.0
        }, 
        "8": {
            "251-300~take": 1.0
        }, 
        "8/13/06": {
            "1886546~D:": 0.5, 
            "8/13/06~T:": 0.5
        }, 
        "87": {
            "rhythm~at": 1.0
        }, 
        "92": {
            "heart~rate": 1.0
        }, 
        "97%": {
            "saturation~is": 1.0
        }, 
        "98.8.": {
            "for~temperature": 1.0
        }, 
        "A": {
            "PRESENT~ILLNESS:": 1.0
        }, 
        "ADMISSION:": {
            "EXAMINATION~ON": 0.5, 
            "MEDICATIONS~ON": 0.5
        }, 
        "ADMISSIONS": {
            "extremity~edema.": 1.0
        }, 
        "AICD": {
            "transplant~and": 1.0
        }, 
        "ALLERGIES:": {
            "mg~b.i.d.": 1.0
        }, 
        "AM": {
            "11/23/2006~12:00:00": 1.0
        }, 
        "ATTENDING:": {
            "Date:~3/26/2006": 1.0
        }, 
        "Admission": {
            "DIS~|": 1.0
        }, 
        "At": {
            "intravascularly~dry.": 1.0
        }, 
        "Attending:": {
            ",~DAMION": 1.0
        }, 
        "BRAYE": {
            "Dictated~By:": 1.0
        }, 
        "BY": {
            "HOSPITAL~COURSE": 1.0
        }, 
        "Baseline": {
            "medication~related.": 1.0
        }, 
        "Blood": {
            "temperature~98.8.": 1.0
        }, 
        "By:": {
            "HFFocus~Dictated": 1.0
        }, 
        "C": {
            ",~Vitamin": 0.5, 
            "MEDICATIONS:~Vitamin": 0.5
        }, 
        "COURSE": {
            "EKGs.~HOSPITAL": 1.0
        }, 
        "Calcium": {
            "ON~ADMISSION:": 1.0
        }, 
        "Cardiomyopathy": {
            "HISTORY:~1.": 1.0
        }, 
        "Cardiovascular": {
            "117.7~kilograms.": 1.0
        }, 
        "Cardiovascular:": {
            "discharge.~2.": 1.0
        }, 
        "Cartia": {
            "night~,": 0.5, 
            "t.i.d.~,": 0.5
        }, 
        "CellCept": {
            "daily~,": 1.0
        }, 
        "Chronic": {
            "placement.~2.": 1.0
        }, 
        "Creatinine": {
            "is~1.8.": 0.5, 
            "renal~failure.": 0.5
        }, 
        "D:": {
            "ID~1886546": 1.0
        }, 
        "DAMION": {
            "BRAYE~,": 1.0
        }, 
        "DIABETES": {
            "NEW~ONSET": 1.0
        }, 
        "DIAGNOSIS:": {
            "RAFAEL~M.D.": 1.0
        }, 
        "DIS": {
            "Unsigned~|": 1.0
        }, 
        "DISCHARGE": {
            "to~1.6.": 1.0
        }, 
        "Date:": {
            "Unsigned~Discharge": 0.5, 
            "|~Admission": 0.5
        }, 
        "Dictated": {
            "5-0284099~HFFocus": 1.0
        }, 
        "Dictation": {
            ",~JUSTIN": 1.0
        }, 
        "Discharge": {
            "Status:~Unsigned": 1.0
        }, 
        "Dr.": {
            "and~with": 1.0
        }, 
        "E": {
            ",~Vitamin": 1.0
        }, 
        "EKG": {
            "potassium~4.9.": 1.0
        }, 
        "EKGs.": {
            "from~prior": 1.0
        }, 
        "EXAMINATION": {
            "\"shaking.\"~PHYSICAL": 1.0
        }, 
        "Endocrine": {
            "new-onset~diabetes.": 1.0
        }, 
        "Endocrine:": {
            "ISSUE:~1.": 1.0
        }, 
        "Glargine": {
            "insulin~(": 1.0
        }, 
        "Gout.": {
            "pancreatitis.~6.": 1.0
        }, 
        "HFFocus": {
            "document:~5-0284099": 1.0
        }, 
        "HISTORY": {
            "New-onset~diabetes": 1.0
        }, 
        "HISTORY:": {
            "PAST~MEDICAL": 1.0
        }, 
        "HOSPITAL": {
            "prior~EKGs.": 1.0
        }, 
        "History": {
            "regurgitation.~5.": 1.0
        }, 
        "Hypothyroidism.": {
            "insufficiency.~3.": 1.0
        }, 
        "ID": {
            "JUSTIN~Dictation": 1.0
        }, 
        "ILLNESS:": {
            "OF~PRESENT": 1.0
        }, 
        "ISSUE:": {
            "COURSE~BY": 1.0
        }, 
        "If": {
            "as~follows:": 1.0
        }, 
        "JUSTIN": {
            "VIDA~,": 1.0
        }, 
        "Jonson": {
            "with~Dr.": 1.0
        }, 
        "K-dur": {
            "daily~,": 1.0
        }, 
        "LABORATORIES:": {
            "edema.~ADMISSIONS": 1.0
        }, 
        "Lantus": {
            "b.i.d.~,": 0.5, 
            "regimen~of": 0.5
        }, 
        "M.D.": {
            ",~RAFAEL": 1.0
        }, 
        "MEDICAL": {
            "negative.~PAST": 1.0
        }, 
        "MEDICATIONS": {
            "6.~Gout.": 1.0
        }, 
        "MEDICATIONS:": {
            "1.6.~DISCHARGE": 1.0
        }, 
        "Mettee": {
            "with~Napoleon": 1.0
        }, 
        "NEW": {
            "AM~|": 1.0
        }, 
        "Napoleon": {
            "followup~with": 1.0
        }, 
        "Neoral": {
            "p.r.n.~,": 1.0
        }, 
        "New-onset": {
            "M.D.~DIAGNOSIS:": 1.0
        }, 
        "No": {
            "sternal~border.": 1.0
        }, 
        "Notable": {
            "ADMISSIONS~LABORATORIES:": 0.5, 
            "ON~ADMISSION:": 0.5
        }, 
        "Novolog": {
            ",~and": 0.16666666666666666, 
            "Lantus~,": 0.16666666666666666, 
            "breakfast~,": 0.16666666666666666, 
            "lunch~,": 0.16666666666666666, 
            "q.a.m.~,": 0.16666666666666666, 
            "with~a": 0.16666666666666666
        }, 
        "OF": {
            "diabetes~HISTORY": 1.0
        }, 
        "ON": {
            "Gout.~MEDICATIONS": 0.5, 
            "PHYSICAL~EXAMINATION": 0.5
        }, 
        "ONSET": {
            "|~NEW": 1.0
        }, 
        "PAST": {
            "is~negative.": 1.0
        }, 
        "PCP": {
            "by~his": 1.0
        }, 
        "PHYSICAL": {
            "to~\"shaking.\"": 1.0
        }, 
        "PRESENT": {
            "HISTORY~OF": 1.0
        }, 
        "Penicillin": {
            "b.i.d.~ALLERGIES:": 1.0
        }, 
        "Pravachol": {
            "daily~,": 1.0
        }, 
        "Pravastatin": {
            "daily~,": 1.0
        }, 
        "RAFAEL": {
            "SPIESS~,": 1.0
        }, 
        "RM": {
            "626012950~|": 1.0
        }, 
        "Regular": {
            "Cardiovascular~examination:": 1.0
        }, 
        "Renal:": {
            "colchicine.~4.": 1.0
        }, 
        "Report": {
            "Date:~10/21/2006": 1.0
        }, 
        "Rheumatology:": {
            "discharge.~3.": 1.0
        }, 
        "Rocaltrol": {
            "b.i.d.~,": 0.5, 
            "daily~,": 0.5
        }, 
        "SPIESS": {
            "3/26/2006~ATTENDING:": 1.0
        }, 
        "Soft": {
            "and~rhythm.": 1.0
        }, 
        "Status:": {
            "10/21/2006~Report": 1.0
        }, 
        "Synthroid": {
            "daily~,": 1.0
        }, 
        "T": {
            "and~anterior": 1.0
        }, 
        "T:": {
            "D:~8/13/06": 1.0
        }, 
        "The": {
            "1.~Endocrine:": 0.1111111111111111, 
            "2.~Cardiovascular:": 0.1111111111111111, 
            "3.~Rheumatology:": 0.1111111111111111, 
            "4.~Renal:": 0.1111111111111111, 
            "home~medications.": 0.1111111111111111, 
            "of~1000.": 0.1111111111111111, 
            "q.~a.c.": 0.1111111111111111, 
            "room~air.": 0.1111111111111111, 
            "sliding~scale.": 0.1111111111111111
        }, 
        "Torsemide": {
            "daily~,": 1.0
        }, 
        "Tricuspid": {
            "Hypothyroidism.~4.": 1.0
        }, 
        "Unsigned": {
            "DIABETES~|": 0.5, 
            "Report~Status:": 0.5
        }, 
        "VIDA": {
            "DAMION~Attending:": 1.0
        }, 
        "VNA": {
            "and~with": 1.0
        }, 
        "Vitamin": {
            "C~,": 0.25, 
            "DISCHARGE~MEDICATIONS:": 0.25, 
            "daily~,": 0.25, 
            "q.a.m.~,": 0.25
        }, 
        "Was": {
            "extremity~edema.": 1.0
        }, 
        "Weight": {
            "well~appearing.": 1.0
        }, 
        "XT": {
            ",~Cartia": 1.0
        }, 
        "a": {
            "2.2~from": 0.14285714285714285, 
            "Notable~for": 0.14285714285714285, 
            "combined~with": 0.14285714285714285, 
            "controlled~with": 0.14285714285714285, 
            "man~with": 0.14285714285714285, 
            "reported~approximately": 0.14285714285714285, 
            "to~have": 0.14285714285714285
        }, 
        "a.c.": {
            "Novolog~q.": 0.5, 
            "scale~q.": 0.5
        }, 
        "acid": {
            ",~folic": 1.0
        }, 
        "acute": {
            "had~mild": 0.5, 
            "to~prerenal": 0.5
        }, 
        "administration": {
            "and~insulin": 1.0
        }, 
        "admission": {
            "Creatinine~at": 0.25, 
            "day~of": 0.25, 
            "flare~during": 0.25, 
            "time~of": 0.25
        }, 
        "aggressively": {
            "he~was": 1.0
        }, 
        "air.": {
            "on~room": 1.0
        }, 
        "also": {
            "The~patient": 1.0
        }, 
        "and": {
            "2002~,": 0.0625, 
            "E~,": 0.0625, 
            "Regular~rate": 0.0625, 
            "aggressively~hydrated": 0.0625, 
            "and~myalgias": 0.0625, 
            "block~,": 0.0625, 
            "cramps~,": 0.0625, 
            "diabetes~clinic": 0.0625, 
            "dinner~,": 0.0625, 
            "familial~cardiomyopathy": 0.0625, 
            "glucose~testing": 0.0625, 
            "of~admission": 0.0625, 
            "post~transplant": 0.0625, 
            "sore~throat": 0.0625, 
            "teaching~nurse": 0.0625, 
            "was~consulted": 0.0625
        }, 
        "anterior": {
            ",~and": 1.0
        }, 
        "appearing.": {
            "but~well": 1.0
        }, 
        "approximately": {
            "and~reported": 1.0
        }, 
        "are": {
            "changes~that": 1.0
        }, 
        "as": {
            "scale~is": 1.0
        }, 
        "assist": {
            "services~to": 1.0
        }, 
        "at": {
            "1.8.~Creatinine": 0.2, 
            "20~mg": 0.2, 
            "failure.~Creatinine": 0.2, 
            "heard~best": 0.2, 
            "sinus~rhythm": 0.2
        }, 
        "atrial": {
            "of~left": 1.0
        }, 
        "b.i.d.": {
            "1500~mg": 0.2222222222222222, 
            "150~mg": 0.3333333333333333, 
            "400~mg": 0.1111111111111111, 
            "420~mg": 0.1111111111111111, 
            "500~mg": 0.1111111111111111, 
            "mg~p.o.": 0.1111111111111111
        }, 
        "baseline": {
            "from~a": 1.0
        }, 
        "beats": {
            "at~87": 1.0
        }, 
        "before": {
            "12~units": 0.6666666666666666, 
            "14~units": 0.3333333333333333
        }, 
        "best": {
            "murmur~heard": 1.0
        }, 
        "block": {
            "right~bundle-branch": 1.0
        }, 
        "blood": {
            ",~if": 0.5714285714285714, 
            "follows:~If": 0.14285714285714285, 
            "for~a": 0.14285714285714285, 
            "understanding~of": 0.14285714285714285
        }, 
        "blurry": {
            "polydipsia~,": 1.0
        }, 
        "border.": {
            "left~sternal": 1.0
        }, 
        "breakfast": {
            "units~before": 1.0
        }, 
        "bundle-branch": {
            "incomplete~right": 1.0
        }, 
        "but": {
            "#obese#~,": 0.5, 
            "days~,": 0.5
        }, 
        "by": {
            "Was~seen": 1.0
        }, 
        "calcium": {
            "daily~,": 1.0
        }, 
        "call": {
            "instructed~to": 1.0
        }, 
        "carbonate": {
            ",~calcium": 0.5, 
            "ADMISSION:~Calcium": 0.5
        }, 
        "cardiac": {
            "status~post": 1.0
        }, 
        "cardiomyopathy": {
            "of~familial": 1.0
        }, 
        "changes": {
            "T~wave": 1.0
        }, 
        "chronic": {
            ",~and": 0.5, 
            "patient~with": 0.5
        }, 
        "clinic": {
            "the~diabetes": 1.0
        }, 
        "colchicine": {
            "b.i.d.~,": 0.5, 
            "t.i.d.~,": 0.5
        }, 
        "colchicine.": {
            "started~on": 1.0
        }, 
        "combination": {
            "with~a": 1.0
        }, 
        "combined": {
            "a.c.~,": 1.0
        }, 
        "consulted": {
            "service~was": 1.0
        }, 
        "controlled": {
            "patient~was": 1.0
        }, 
        "cough": {
            "throat~and": 1.0
        }, 
        "cramps": {
            ",~muscle": 1.0
        }, 
        "creatinine": {
            "1064~,": 0.5, 
            "related.~Baseline": 0.5
        }, 
        "cyclosporin": {
            ",~and": 0.5, 
            "b.i.d.~,": 0.5
        }, 
        "daily": {
            "0.25~mcg": 0.06666666666666667, 
            "0.25~mg": 0.06666666666666667, 
            "0.6~mg": 0.06666666666666667, 
            "150~mcg": 0.13333333333333333, 
            "1~mg": 0.13333333333333333, 
            "2.5~mg": 0.06666666666666667, 
            "20~mg": 0.13333333333333333, 
            "300~mg": 0.13333333333333333, 
            "400~units": 0.06666666666666667, 
            "40~mg": 0.06666666666666667, 
            "7~mg": 0.06666666666666667
        }, 
        "day": {
            "on~the": 1.0
        }, 
        "days": {
            "times~several": 1.0
        }, 
        "decrease": {
            "weeks~with": 1.0
        }, 
        "demonstrated": {
            "The~patient": 1.0
        }, 
        "diabetes": {
            "DIAGNOSIS:~New-onset": 0.5, 
            "in~the": 0.5
        }, 
        "diabetes.": {
            "with~new-onset": 1.0
        }, 
        "diabetic": {
            ",~the": 1.0
        }, 
        "diltiazem": {
            "that~is": 1.0
        }, 
        "dinner": {
            "units~before": 1.0
        }, 
        "discharge": {
            "Creatinine~at": 1.0
        }, 
        "discharge.": {
            "prior~to": 1.0
        }, 
        "discharged": {
            "patient~was": 1.0
        }, 
        "doctor.": {
            "call~his": 1.0
        }, 
        "document:": {
            "doctor.~eScription": 1.0
        }, 
        "dry.": {
            "was~intravascularly": 1.0
        }, 
        "during": {
            "gout~flare": 1.0
        }, 
        "eScription": {
            "his~doctor.": 1.0
        }, 
        "edema.": {
            "lower~extremity": 1.0
        }, 
        "enlargement": {
            "left~atrial": 1.0
        }, 
        "euvolemic": {
            "hydrated~and": 1.0
        }, 
        "evidence": {
            "minute~,": 1.0
        }, 
        "examination:": {
            "kilograms.~Cardiovascular": 1.0
        }, 
        "extended": {
            "is~diltiazem": 1.0
        }, 
        "extremity": {
            "No~lower": 0.5, 
            "usual~lower": 0.5
        }, 
        "failure.": {
            "acute~renal": 1.0
        }, 
        "familial": {
            "history~of": 1.0
        }, 
        "fingerstick": {
            "have~a": 1.0
        }, 
        "flare": {
            "acute~gout": 1.0
        }, 
        "folate": {
            "b.i.d.~,": 1.0
        }, 
        "folic": {
            "b.i.d.~,": 1.0
        }, 
        "follows:": {
            "is~as": 1.0
        }, 
        "followup": {
            "discharged~with": 1.0
        }, 
        "for": {
            "ADMISSION:~Notable": 0.3333333333333333, 
            "LABORATORIES:~Notable": 0.3333333333333333, 
            "during~admission": 0.3333333333333333
        }, 
        "found": {
            "admission~and": 1.0
        }, 
        "from": {
            "are~unchanged": 0.5, 
            "creatinine~2.2": 0.5
        }, 
        "glucose": {
            "a~blood": 0.5, 
            "of~blood": 0.5
        }, 
        "gout": {
            "mild~acute": 1.0
        }, 
        "greater": {
            "it~is": 0.5, 
            "presented~with": 0.5
        }, 
        "had": {
            "The~patient": 0.5, 
            "at~discharge": 0.5
        }, 
        "have": {
            "found~to": 1.0
        }, 
        "he": {
            "admission~,": 0.5, 
            "for~which": 0.5
        }, 
        "heard": {
            "systolic~murmur": 1.0
        }, 
        "heart": {
            "140/82~,": 1.0
        }, 
        "his": {
            "seen~by": 0.5, 
            "to~call": 0.5
        }, 
        "history": {
            "with~a": 1.0
        }, 
        "home": {
            "assist~with": 1.0
        }, 
        "hydrated": {
            "was~aggressively": 1.0
        }, 
        "if": {
            "units~,": 1.0
        }, 
        "immunosuppression": {
            "transplant~,": 1.0
        }, 
        "in": {
            "Dr.~Jonson": 0.3333333333333333, 
            "cardiac~transplant": 0.3333333333333333, 
            "with~decrease": 0.3333333333333333
        }, 
        "incomplete": {
            "enlargement~,": 1.0
        }, 
        "instructed": {
            "patient~is": 1.0
        }, 
        "insufficiency": {
            "chronic~renal": 1.0
        }, 
        "insufficiency.": {
            "Chronic~renal": 1.0
        }, 
        "insulin": {
            ",~Lantus": 0.5, 
            "testing~and": 0.5
        }, 
        "intravascularly": {
            "patient~was": 1.0
        }, 
        "is": {
            ",~saturation": 0.07692307692307693, 
            "Baseline~creatinine": 0.07692307692307693, 
            "The~patient": 0.07692307692307693, 
            "XT~that": 0.07692307692307693, 
            "blood~sugar": 0.38461538461538464, 
            "if~it": 0.07692307692307693, 
            "of~systems": 0.07692307692307693, 
            "sliding~scale": 0.07692307692307693, 
            "the~patient": 0.07692307692307693
        }, 
        "it": {
            ",~if": 1.0
        }, 
        "kilograms.": {
            "Weight~117.7": 1.0
        }, 
        "leads": {
            "ALLERGIES:~Penicillin": 1.0
        }, 
        "left": {
            "at~the": 0.5, 
            "evidence~of": 0.5
        }, 
        "likely": {
            "insufficiency~,": 0.5, 
            "of~2.2": 0.5
        }, 
        "loss": {
            "15-pound~weight": 1.0
        }, 
        "lower": {
            "border.~No": 0.5, 
            "in~usual": 0.5
        }, 
        "lunch": {
            "units~before": 1.0
        }, 
        "magnesium": {
            "daily~,": 1.0
        }, 
        "man": {
            "A~45-year-old": 1.0
        }, 
        "mcg": {
            "Rocaltrol~0.25": 0.3333333333333333, 
            "Synthroid~150": 0.6666666666666666
        }, 
        "medication": {
            ",~immunosuppression": 1.0
        }, 
        "medications.": {
            "with~home": 1.0
        }, 
        "methotrexate": {
            "b.i.d.~,": 1.0
        }, 
        "mg": {
            "CellCept~1500": 0.08, 
            "C~500": 0.04, 
            "K-dur~20": 0.04, 
            "Neoral~150": 0.04, 
            "Pravachol~20": 0.04, 
            "Pravastatin~20": 0.04, 
            "Rocaltrol~0.25": 0.04, 
            "Torsemide~40": 0.04, 
            "XT~300": 0.04, 
            "acid~1": 0.04, 
            "carbonate~1250": 0.04, 
            "carbonate~500": 0.04, 
            "colchicine~0.3": 0.04, 
            "colchicine~0.6": 0.04, 
            "cyclosporin~150": 0.08, 
            "folate~1": 0.04, 
            "is~201-250": 0.04, 
            "methotrexate~2.5": 0.04, 
            "oxide~400": 0.04, 
            "oxide~420": 0.04, 
            "prednisone~7": 0.04, 
            "prednisone~7.5": 0.04, 
            "release~300": 0.04
        }, 
        "mild": {
            "patient~had": 1.0
        }, 
        "minute": {
            "beats~per": 1.0
        }, 
        "murmur": {
            "2/6~systolic": 1.0
        }, 
        "muscle": {
            "vision~,": 1.0
        }, 
        "myalgias": {
            ",~and": 1.0
        }, 
        "negative.": {
            "systems~is": 1.0
        }, 
        "new-onset": {
            "patient~with": 1.0
        }, 
        "night": {
            "mg~at": 1.0
        }, 
        "normal": {
            "4.9.~EKG": 1.0
        }, 
        "normalized": {
            "discharge~had": 1.0
        }, 
        "nurse": {
            "diabetic~teaching": 1.0
        }, 
        "of": {
            ",~evidence": 0.07692307692307693, 
            "5.~History": 0.07692307692307693, 
            "at~admission": 0.07692307692307693, 
            "a~baseline": 0.07692307692307693, 
            "a~fingerstick": 0.07692307692307693, 
            "a~history": 0.07692307692307693, 
            "blood~glucose": 0.07692307692307693, 
            "combination~regimen": 0.07692307692307693, 
            "otherwise~review": 0.07692307692307693, 
            "proper~understanding": 0.07692307692307693, 
            "the~day": 0.07692307692307693, 
            "the~time": 0.07692307692307693, 
            "two~weeks": 0.07692307692307693
        }, 
        "on": {
            "his~PCP": 0.3333333333333333, 
            "is~97%": 0.3333333333333333, 
            "was~started": 0.3333333333333333
        }, 
        "otherwise": {
            ",~but": 1.0
        }, 
        "over": {
            "weight~loss": 1.0
        }, 
        "oxide": {
            ",~magnesium": 1.0
        }, 
        "p.o.": {
            "0.3~mg": 1.0
        }, 
        "p.r.n.": {
            "mg~daily": 1.0
        }, 
        "pancreatitis.": {
            "History~of": 1.0
        }, 
        "patient": {
            ",~the": 0.1, 
            "1000.~The": 0.1, 
            "Cardiovascular:~The": 0.1, 
            "Endocrine:~The": 0.1, 
            "Renal:~The": 0.1, 
            "Rheumatology:~The": 0.1, 
            "air.~The": 0.1, 
            "and~the": 0.1, 
            "medications.~The": 0.1, 
            "scale.~The": 0.1
        }, 
        "per": {
            "87~beats": 1.0
        }, 
        "placement.": {
            "and~AICD": 1.0
        }, 
        "polydipsia": {
            "polyuria~,": 1.0
        }, 
        "polyuria": {
            "weeks~of": 1.0
        }, 
        "post": {
            ",~status": 0.5, 
            "and~status": 0.5
        }, 
        "potassium": {
            "130~,": 1.0
        }, 
        "prednisone": {
            "b.i.d.~,": 0.5, 
            "daily~,": 0.5
        }, 
        "prerenal": {
            "related~to": 1.0
        }, 
        "presented": {
            "renal~insufficiency": 1.0
        }, 
        "pressure": {
            "98.8.~Blood": 1.0
        }, 
        "prior": {
            "and~euvolemic": 0.3333333333333333, 
            "insulin~administration": 0.3333333333333333, 
            "unchanged~from": 0.3333333333333333
        }, 
        "proper": {
            "patient~demonstrated": 1.0
        }, 
        "q.": {
            ",~Novolog": 0.5, 
            "sliding~scale": 0.5
        }, 
        "q.a.m.": {
            "7.5~mg": 0.5, 
            "units~subcutaneous": 0.5
        }, 
        "rate": {
            ",~heart": 0.5, 
            "examination:~Regular": 0.5
        }, 
        "regimen": {
            "a~combination": 1.0
        }, 
        "regurgitation.": {
            "4.~Tricuspid": 1.0
        }, 
        "related": {
            "2.2~likely": 1.0
        }, 
        "related.": {
            "immunosuppression~medication": 1.0
        }, 
        "release": {
            "diltiazem~extended": 1.0
        }, 
        "renal": {
            "2.~Chronic": 0.25, 
            "and~chronic": 0.25, 
            "prerenal~acute": 0.25, 
            "with~chronic": 0.25
        }, 
        "reported": {
            "myalgias~and": 0.5, 
            "patient~also": 0.5
        }, 
        "review": {
            "but~otherwise": 1.0
        }, 
        "rhythm": {
            "normal~sinus": 1.0
        }, 
        "rhythm.": {
            "rate~and": 1.0
        }, 
        "right": {
            ",~incomplete": 1.0
        }, 
        "room": {
            "97%~on": 1.0
        }, 
        "saturation": {
            "92~,": 1.0
        }, 
        "scale": {
            "Novolog~sliding": 0.5, 
            "The~sliding": 0.5
        }, 
        "scale.": {
            "Novolog~sliding": 1.0
        }, 
        "seen": {
            "edema.~Was": 1.0
        }, 
        "service": {
            "diabetes.~Endocrine": 1.0
        }, 
        "services": {
            "with~VNA": 1.0
        }, 
        "several": {
            "cough~times": 1.0
        }, 
        "sinus": {
            "EKG~normal": 1.0
        }, 
        "sliding": {
            "a.c.~The": 0.3333333333333333, 
            "and~Novolog": 0.3333333333333333, 
            "a~Novolog": 0.3333333333333333
        }, 
        "sodium": {
            "1.8~,": 1.0
        }, 
        "sore": {
            "also~reported": 1.0
        }, 
        "started": {
            "he~was": 1.0
        }, 
        "status": {
            "Cardiomyopathy~,": 0.5, 
            "cardiomyopathy~and": 0.5
        }, 
        "sternal": {
            "the~left": 1.0
        }, 
        "subcutaneous": {
            "40~units": 1.0
        }, 
        "sugar": {
            "If~blood": 0.2, 
            "if~blood": 0.8
        }, 
        "systems": {
            "review~of": 1.0
        }, 
        "systolic": {
            ",~2/6": 1.0
        }, 
        "t.i.d.": {
            "1250~mg": 0.5, 
            "500~mg": 0.5
        }, 
        "take": {
            "201-250~mg": 0.2, 
            "is~150-200": 0.2, 
            "is~251-300": 0.2, 
            "is~301-350": 0.2, 
            "is~350-400": 0.2
        }, 
        "teaching": {
            "the~diabetic": 1.0
        }, 
        "temperature": {
            "Notable~for": 1.0
        }, 
        "testing": {
            "blood~glucose": 1.0
        }, 
        "than": {
            "is~greater": 0.5, 
            "with~greater": 0.5
        }, 
        "that": {
            "Cartia~XT": 0.5, 
            "wave~changes": 0.5
        }, 
        "the": {
            "400~,": 0.14285714285714285, 
            "Jonson~in": 0.14285714285714285, 
            "Mettee~,": 0.14285714285714285, 
            "PCP~on": 0.14285714285714285, 
            "best~at": 0.14285714285714285, 
            "consulted~and": 0.14285714285714285, 
            "dry.~At": 0.14285714285714285
        }, 
        "three": {
            "loss~over": 1.0
        }, 
        "throat": {
            "reported~sore": 1.0
        }, 
        "time": {
            "At~the": 1.0
        }, 
        "times": {
            "and~cough": 1.0
        }, 
        "to": {
            "Penicillin~leads": 0.125, 
            "VNA~services": 0.125, 
            "administration~prior": 0.125, 
            "and~found": 0.125, 
            "euvolemic~prior": 0.125, 
            "had~normalized": 0.125, 
            "is~instructed": 0.125, 
            "likely~related": 0.125
        }, 
        "transplant": {
            ",~likely": 0.3333333333333333, 
            "post~cardiac": 0.3333333333333333, 
            "status~post": 0.3333333333333333
        }, 
        "two": {
            "greater~than": 1.0
        }, 
        "unchanged": {
            "that~are": 1.0
        }, 
        "understanding": {
            "demonstrated~proper": 1.0
        }, 
        "units": {
            ")~40": 0.1, 
            "E~400": 0.1, 
            "Novolog~12": 0.2, 
            "Novolog~14": 0.1, 
            "take~10": 0.1, 
            "take~12": 0.1, 
            "take~4": 0.1, 
            "take~6": 0.1, 
            "take~8": 0.1
        }, 
        "usual": {
            "decrease~in": 1.0
        }, 
        "vision": {
            ",~blurry": 1.0
        }, 
        "was": {
            ",~he": 0.16666666666666666, 
            "Endocrine~service": 0.16666666666666666, 
            "The~patient": 0.3333333333333333, 
            "the~patient": 0.16666666666666666, 
            "which~he": 0.16666666666666666
        }, 
        "wave": {
            "anterior~T": 1.0
        }, 
        "weeks": {
            "over~three": 0.5, 
            "than~two": 0.5
        }, 
        "weight": {
            "a~15-pound": 1.0
        }, 
        "well": {
            ",~but": 1.0
        }, 
        "which": {
            "admission~for": 1.0
        }, 
        "with": {
            ",~combined": 0.08333333333333333, 
            "45-year-old~man": 0.08333333333333333, 
            "The~patient": 0.16666666666666666, 
            "clinic~and": 0.08333333333333333, 
            "insufficiency~presented": 0.08333333333333333, 
            "nurse~and": 0.08333333333333333, 
            "three~weeks": 0.08333333333333333, 
            "to~assist": 0.08333333333333333, 
            "was~controlled": 0.08333333333333333, 
            "was~discharged": 0.08333333333333333, 
            "with~followup": 0.08333333333333333
        }, 
        "|": {
            "12:00:00~AM": 0.1111111111111111, 
            "41614963~|": 0.1111111111111111, 
            "ONSET~DIABETES": 0.1111111111111111, 
            "|~1243403": 0.1111111111111111, 
            "|~41614963": 0.1111111111111111, 
            "|~DIS": 0.1111111111111111, 
            "|~RM": 0.1111111111111111, 
            "|~Unsigned": 0.1111111111111111, 
            "~626012950": 0.1111111111111111
        }
    }, 
    "type": "data/train", 
    "uni": {
        "": 0.001375515818431912, 
        "\"shaking.\"": 0.001375515818431912, 
        "#obese#": 0.001375515818431912, 
        "(": 0.001375515818431912, 
        ")": 0.001375515818431912, 
        ",": 0.08940852819807428, 
        "0.25": 0.002751031636863824, 
        "0.3": 0.001375515818431912, 
        "0.6": 0.001375515818431912, 
        "1": 0.002751031636863824, 
        "1.": 0.002751031636863824, 
        "1.6.": 0.001375515818431912, 
        "1.8": 0.001375515818431912, 
        "1.8.": 0.001375515818431912, 
        "10": 0.001375515818431912, 
        "10/21/2006": 0.001375515818431912, 
        "1000.": 0.001375515818431912, 
        "1064": 0.001375515818431912, 
        "11/23/2006": 0.001375515818431912, 
        "117.7": 0.001375515818431912, 
        "12": 0.0041265474552957355, 
        "1243403": 0.001375515818431912, 
        "1250": 0.001375515818431912, 
        "12:00:00": 0.001375515818431912, 
        "130": 0.001375515818431912, 
        "14": 0.001375515818431912, 
        "140/82": 0.001375515818431912, 
        "15-pound": 0.001375515818431912, 
        "150": 0.0068775790921595595, 
        "150-200": 0.001375515818431912, 
        "1500": 0.002751031636863824, 
        "1886546": 0.001375515818431912, 
        "2.": 0.002751031636863824, 
        "2.2": 0.002751031636863824, 
        "2.5": 0.001375515818431912, 
        "2/6": 0.001375515818431912, 
        "20": 0.0041265474552957355, 
        "2002": 0.001375515818431912, 
        "201-250": 0.001375515818431912, 
        "251-300": 0.001375515818431912, 
        "3.": 0.002751031636863824, 
        "3/26/2006": 0.001375515818431912, 
        "300": 0.002751031636863824, 
        "301-350": 0.001375515818431912, 
        "350-400": 0.001375515818431912, 
        "4": 0.001375515818431912, 
        "4.": 0.002751031636863824, 
        "4.9.": 0.001375515818431912, 
        "40": 0.002751031636863824, 
        "400": 0.0041265474552957355, 
        "41614963": 0.001375515818431912, 
        "420": 0.001375515818431912, 
        "45-year-old": 0.001375515818431912, 
        "5-0284099": 0.001375515818431912, 
        "5.": 0.001375515818431912, 
        "500": 0.002751031636863824, 
        "6": 0.001375515818431912, 
        "6.": 0.001375515818431912, 
        "626012950": 0.001375515818431912, 
        "7": 0.001375515818431912, 
        "7.5": 0.001375515818431912, 
        "8": 0.001375515818431912, 
        "8/13/06": 0.001375515818431912, 
        "87": 0.001375515818431912, 
        "92": 0.001375515818431912, 
        "97%": 0.001375515818431912, 
        "98.8.": 0.001375515818431912, 
        "A": 0.001375515818431912, 
        "ADMISSION:": 0.002751031636863824, 
        "ADMISSIONS": 0.001375515818431912, 
        "AICD": 0.001375515818431912, 
        "ALLERGIES:": 0.001375515818431912, 
        "AM": 0.001375515818431912, 
        "ATTENDING:": 0.001375515818431912, 
        "Admission": 0.001375515818431912, 
        "At": 0.001375515818431912, 
        "Attending:": 0.001375515818431912, 
        "BRAYE": 0.001375515818431912, 
        "BY": 0.001375515818431912, 
        "Baseline": 0.001375515818431912, 
        "Blood": 0.001375515818431912, 
        "By:": 0.001375515818431912, 
        "C": 0.002751031636863824, 
        "COURSE": 0.001375515818431912, 
        "Calcium": 0.001375515818431912, 
        "Cardiomyopathy": 0.001375515818431912, 
        "Cardiovascular": 0.001375515818431912, 
        "Cardiovascular:": 0.001375515818431912, 
        "Cartia": 0.002751031636863824, 
        "CellCept": 0.002751031636863824, 
        "Chronic": 0.001375515818431912, 
        "Creatinine": 0.002751031636863824, 
        "D:": 0.001375515818431912, 
        "DAMION": 0.001375515818431912, 
        "DIABETES": 0.001375515818431912, 
        "DIAGNOSIS:": 0.001375515818431912, 
        "DIS": 0.001375515818431912, 
        "DISCHARGE": 0.001375515818431912, 
        "Date:": 0.002751031636863824, 
        "Dictated": 0.001375515818431912, 
        "Dictation": 0.001375515818431912, 
        "Discharge": 0.001375515818431912, 
        "Dr.": 0.001375515818431912, 
        "E": 0.002751031636863824, 
        "EKG": 0.001375515818431912, 
        "EKGs.": 0.001375515818431912, 
        "EXAMINATION": 0.001375515818431912, 
        "Endocrine": 0.001375515818431912, 
        "Endocrine:": 0.001375515818431912, 
        "Glargine": 0.001375515818431912, 
        "Gout.": 0.001375515818431912, 
        "HFFocus": 0.001375515818431912, 
        "HISTORY": 0.001375515818431912, 
        "HISTORY:": 0.001375515818431912, 
        "HOSPITAL": 0.001375515818431912, 
        "History": 0.001375515818431912, 
        "Hypothyroidism.": 0.001375515818431912, 
        "ID": 0.001375515818431912, 
        "ILLNESS:": 0.001375515818431912, 
        "ISSUE:": 0.001375515818431912, 
        "If": 0.001375515818431912, 
        "JUSTIN": 0.001375515818431912, 
        "Jonson": 0.001375515818431912, 
        "K-dur": 0.001375515818431912, 
        "LABORATORIES:": 0.001375515818431912, 
        "Lantus": 0.002751031636863824, 
        "M.D.": 0.001375515818431912, 
        "MEDICAL": 0.001375515818431912, 
        "MEDICATIONS": 0.001375515818431912, 
        "MEDICATIONS:": 0.001375515818431912, 
        "Mettee": 0.001375515818431912, 
        "NEW": 0.001375515818431912, 
        "Napoleon": 0.001375515818431912, 
        "Neoral": 0.001375515818431912, 
        "New-onset": 0.001375515818431912, 
        "No": 0.001375515818431912, 
        "Notable": 0.002751031636863824, 
        "Novolog": 0.008253094910591471, 
        "OF": 0.001375515818431912, 
        "ON": 0.002751031636863824, 
        "ONSET": 0.001375515818431912, 
        "PAST": 0.001375515818431912, 
        "PCP": 0.001375515818431912, 
        "PHYSICAL": 0.001375515818431912, 
        "PRESENT": 0.001375515818431912, 
        "Penicillin": 0.001375515818431912, 
        "Pravachol": 0.001375515818431912, 
        "Pravastatin": 0.001375515818431912, 
        "RAFAEL": 0.001375515818431912, 
        "RM": 0.001375515818431912, 
        "Regular": 0.001375515818431912, 
        "Renal:": 0.001375515818431912, 
        "Report": 0.001375515818431912, 
        "Rheumatology:": 0.001375515818431912, 
        "Rocaltrol": 0.002751031636863824, 
        "SPIESS": 0.001375515818431912, 
        "Soft": 0.001375515818431912, 
        "Status:": 0.001375515818431912, 
        "Synthroid": 0.002751031636863824, 
        "T": 0.001375515818431912, 
        "The": 0.012379642365887207, 
        "Torsemide": 0.001375515818431912, 
        "Tricuspid": 0.001375515818431912, 
        "Unsigned": 0.002751031636863824, 
        "VIDA": 0.001375515818431912, 
        "VNA": 0.001375515818431912, 
        "Vitamin": 0.005502063273727648, 
        "Was": 0.001375515818431912, 
        "Weight": 0.001375515818431912, 
        "XT": 0.002751031636863824, 
        "a": 0.009628610729023384, 
        "a.c.": 0.002751031636863824, 
        "acid": 0.001375515818431912, 
        "acute": 0.002751031636863824, 
        "administration": 0.001375515818431912, 
        "admission": 0.005502063273727648, 
        "aggressively": 0.001375515818431912, 
        "air.": 0.001375515818431912, 
        "also": 0.001375515818431912, 
        "and": 0.02200825309491059, 
        "anterior": 0.001375515818431912, 
        "appearing.": 0.001375515818431912, 
        "approximately": 0.001375515818431912, 
        "are": 0.001375515818431912, 
        "as": 0.001375515818431912, 
        "assist": 0.001375515818431912, 
        "at": 0.0068775790921595595, 
        "atrial": 0.001375515818431912, 
        "b.i.d.": 0.012379642365887207, 
        "baseline": 0.001375515818431912, 
        "beats": 0.001375515818431912, 
        "before": 0.0041265474552957355, 
        "best": 0.001375515818431912, 
        "block": 0.001375515818431912, 
        "blood": 0.009628610729023384, 
        "blurry": 0.001375515818431912, 
        "border.": 0.001375515818431912, 
        "breakfast": 0.001375515818431912, 
        "bundle-branch": 0.001375515818431912, 
        "but": 0.002751031636863824, 
        "by": 0.001375515818431912, 
        "calcium": 0.001375515818431912, 
        "call": 0.001375515818431912, 
        "carbonate": 0.002751031636863824, 
        "cardiac": 0.001375515818431912, 
        "cardiomyopathy": 0.001375515818431912, 
        "changes": 0.001375515818431912, 
        "chronic": 0.002751031636863824, 
        "clinic": 0.001375515818431912, 
        "colchicine": 0.002751031636863824, 
        "colchicine.": 0.001375515818431912, 
        "combination": 0.001375515818431912, 
        "combined": 0.001375515818431912, 
        "consulted": 0.001375515818431912, 
        "controlled": 0.001375515818431912, 
        "cough": 0.001375515818431912, 
        "cramps": 0.001375515818431912, 
        "creatinine": 0.002751031636863824, 
        "cyclosporin": 0.002751031636863824, 
        "daily": 0.02063273727647868, 
        "day": 0.001375515818431912, 
        "days": 0.001375515818431912, 
        "decrease": 0.001375515818431912, 
        "demonstrated": 0.001375515818431912, 
        "diabetes": 0.002751031636863824, 
        "diabetes.": 0.001375515818431912, 
        "diabetic": 0.001375515818431912, 
        "diltiazem": 0.001375515818431912, 
        "dinner": 0.001375515818431912, 
        "discharge": 0.001375515818431912, 
        "discharge.": 0.002751031636863824, 
        "discharged": 0.001375515818431912, 
        "doctor.": 0.001375515818431912, 
        "document:": 0.001375515818431912, 
        "dry.": 0.001375515818431912, 
        "during": 0.001375515818431912, 
        "eScription": 0.001375515818431912, 
        "edema.": 0.002751031636863824, 
        "enlargement": 0.001375515818431912, 
        "euvolemic": 0.001375515818431912, 
        "evidence": 0.001375515818431912, 
        "examination:": 0.001375515818431912, 
        "extended": 0.001375515818431912, 
        "extremity": 0.002751031636863824, 
        "failure.": 0.001375515818431912, 
        "familial": 0.001375515818431912, 
        "fingerstick": 0.001375515818431912, 
        "flare": 0.001375515818431912, 
        "folate": 0.001375515818431912, 
        "folic": 0.001375515818431912, 
        "follows:": 0.001375515818431912, 
        "followup": 0.001375515818431912, 
        "for": 0.0041265474552957355, 
        "found": 0.001375515818431912, 
        "from": 0.002751031636863824, 
        "glucose": 0.002751031636863824, 
        "gout": 0.001375515818431912, 
        "greater": 0.002751031636863824, 
        "had": 0.002751031636863824, 
        "have": 0.001375515818431912, 
        "he": 0.002751031636863824, 
        "heard": 0.001375515818431912, 
        "heart": 0.001375515818431912, 
        "his": 0.002751031636863824, 
        "history": 0.001375515818431912, 
        "home": 0.001375515818431912, 
        "hydrated": 0.001375515818431912, 
        "if": 0.0068775790921595595, 
        "immunosuppression": 0.001375515818431912, 
        "in": 0.0041265474552957355, 
        "incomplete": 0.001375515818431912, 
        "instructed": 0.001375515818431912, 
        "insufficiency": 0.002751031636863824, 
        "insufficiency.": 0.001375515818431912, 
        "insulin": 0.002751031636863824, 
        "intravascularly": 0.001375515818431912, 
        "is": 0.017881705639614855, 
        "it": 0.001375515818431912, 
        "kilograms.": 0.001375515818431912, 
        "leads": 0.001375515818431912, 
        "left": 0.002751031636863824, 
        "likely": 0.002751031636863824, 
        "loss": 0.001375515818431912, 
        "lower": 0.002751031636863824, 
        "lunch": 0.001375515818431912, 
        "magnesium": 0.002751031636863824, 
        "man": 0.001375515818431912, 
        "mcg": 0.0041265474552957355, 
        "medication": 0.001375515818431912, 
        "medications.": 0.001375515818431912, 
        "methotrexate": 0.001375515818431912, 
        "mg": 0.0343878954607978, 
        "mild": 0.001375515818431912, 
        "minute": 0.001375515818431912, 
        "murmur": 0.001375515818431912, 
        "muscle": 0.001375515818431912, 
        "myalgias": 0.001375515818431912, 
        "negative.": 0.001375515818431912, 
        "new-onset": 0.001375515818431912, 
        "night": 0.001375515818431912, 
        "normal": 0.001375515818431912, 
        "normalized": 0.001375515818431912, 
        "nurse": 0.001375515818431912, 
        "of": 0.017881705639614855, 
        "on": 0.0041265474552957355, 
        "otherwise": 0.001375515818431912, 
        "over": 0.001375515818431912, 
        "oxide": 0.002751031636863824, 
        "p.o.": 0.001375515818431912, 
        "p.r.n.": 0.001375515818431912, 
        "pancreatitis.": 0.001375515818431912, 
        "patient": 0.013755158184319119, 
        "per": 0.001375515818431912, 
        "placement.": 0.001375515818431912, 
        "polydipsia": 0.001375515818431912, 
        "polyuria": 0.001375515818431912, 
        "post": 0.002751031636863824, 
        "potassium": 0.001375515818431912, 
        "prednisone": 0.002751031636863824, 
        "prerenal": 0.001375515818431912, 
        "presented": 0.001375515818431912, 
        "pressure": 0.001375515818431912, 
        "prior": 0.0041265474552957355, 
        "proper": 0.001375515818431912, 
        "q.": 0.002751031636863824, 
        "q.a.m.": 0.002751031636863824, 
        "rate": 0.002751031636863824, 
        "regimen": 0.001375515818431912, 
        "regurgitation.": 0.001375515818431912, 
        "related": 0.001375515818431912, 
        "related.": 0.001375515818431912, 
        "release": 0.001375515818431912, 
        "renal": 0.005502063273727648, 
        "reported": 0.002751031636863824, 
        "review": 0.001375515818431912, 
        "rhythm": 0.001375515818431912, 
        "rhythm.": 0.001375515818431912, 
        "right": 0.001375515818431912, 
        "room": 0.001375515818431912, 
        "saturation": 0.001375515818431912, 
        "scale": 0.002751031636863824, 
        "scale.": 0.001375515818431912, 
        "seen": 0.001375515818431912, 
        "service": 0.001375515818431912, 
        "services": 0.001375515818431912, 
        "several": 0.001375515818431912, 
        "sinus": 0.001375515818431912, 
        "sliding": 0.0041265474552957355, 
        "sodium": 0.001375515818431912, 
        "sore": 0.001375515818431912, 
        "started": 0.001375515818431912, 
        "status": 0.002751031636863824, 
        "sternal": 0.001375515818431912, 
        "subcutaneous": 0.001375515818431912, 
        "sugar": 0.0068775790921595595, 
        "systems": 0.001375515818431912, 
        "systolic": 0.001375515818431912, 
        "t.i.d.": 0.002751031636863824, 
        "take": 0.0068775790921595595, 
        "teaching": 0.001375515818431912, 
        "temperature": 0.001375515818431912, 
        "testing": 0.001375515818431912, 
        "than": 0.002751031636863824, 
        "that": 0.002751031636863824, 
        "the": 0.009628610729023384, 
        "three": 0.001375515818431912, 
        "throat": 0.001375515818431912, 
        "time": 0.001375515818431912, 
        "times": 0.001375515818431912, 
        "to": 0.011004126547455296, 
        "transplant": 0.0041265474552957355, 
        "two": 0.001375515818431912, 
        "unchanged": 0.001375515818431912, 
        "understanding": 0.001375515818431912, 
        "units": 0.013755158184319119, 
        "usual": 0.001375515818431912, 
        "vision": 0.001375515818431912, 
        "was": 0.008253094910591471, 
        "wave": 0.001375515818431912, 
        "weeks": 0.002751031636863824, 
        "weight": 0.001375515818431912, 
        "well": 0.001375515818431912, 
        "which": 0.001375515818431912, 
        "with": 0.016506189821182942, 
        "|": 0.012379642365887207
    }
}